odoo/addons/hr_timesheet_portal/README.rst
odoo/addons/hr_timesheet_portal/__init__.py
odoo/addons/hr_timesheet_portal/__manifest__.py
odoo/addons/hr_timesheet_portal/demo/hr_timesheet_portal.xml
odoo/addons/hr_timesheet_portal/i18n/hr_timesheet_portal.pot
odoo/addons/hr_timesheet_portal/readme/CONFIGURE.rst
odoo/addons/hr_timesheet_portal/readme/CONTRIBUTORS.rst
odoo/addons/hr_timesheet_portal/readme/DESCRIPTION.rst
odoo/addons/hr_timesheet_portal/readme/newsfragments/.gitkeep
odoo/addons/hr_timesheet_portal/security/hr_timesheet_portal_security.xml
odoo/addons/hr_timesheet_portal/security/ir.model.access.csv
odoo/addons/hr_timesheet_portal/static/description/icon.png
odoo/addons/hr_timesheet_portal/static/description/index.html
odoo/addons/hr_timesheet_portal/static/src/css/hr_timesheet_portal.css
odoo/addons/hr_timesheet_portal/static/src/js/hr_timesheet_portal.js
odoo/addons/hr_timesheet_portal/templates/assets.xml
odoo/addons/hr_timesheet_portal/templates/portal.xml
odoo12_addon_hr_timesheet_portal-12.0.1.0.1.dist-info/METADATA
odoo12_addon_hr_timesheet_portal-12.0.1.0.1.dist-info/WHEEL
odoo12_addon_hr_timesheet_portal-12.0.1.0.1.dist-info/top_level.txt
odoo12_addon_hr_timesheet_portal-12.0.1.0.1.dist-info/RECORD
